LICENSE
MANIFEST.in
README.rst
setup.py
celery_clearcache/__init__.py
celery_clearcache/tasks.py
django_celery_clearcache.egg-info/PKG-INFO
django_celery_clearcache.egg-info/SOURCES.txt
django_celery_clearcache.egg-info/dependency_links.txt
django_celery_clearcache.egg-info/top_level.txt